{"top": [{"name": "konxi", "gold": "2445", "wins": "51", "def": "14", "dead": "1", "score": "109108"}, {"name": "admin", "gold": "299", "wins": "18", "def": "20", "dead": "0", "score": "13455"}, {"name": "admin", "gold": "450", "wins": "13", "def": "8", "dead": "0", "score": "5850"}, {"name": "admin", "gold": "273", "wins": "10", "def": "6", "dead": "0", "score": "2047"}, {"name": "admin", "gold": "378", "wins": "9", "def": "4", "dead": "0", "score": "1701"}, {"name": "admin", "gold": "364", "wins": "9", "def": "4", "dead": "0", "score": "1638"}, {"name": "admin", "gold": "202", "wins": "8", "def": "8", "dead": "0", "score": "1616"}, {"name": "admin", "gold": "236", "wins": "6", "def": "4", "dead": "0", "score": "708"}, {"name": "admin", "gold": "312", "wins": "8", "def": "2", "dead": "0", "score": "624"}, {"name": "admin", "gold": "235", "wins": "6", "def": "2", "dead": "0", "score": "352"}]}